figular/__init__.py
figular/command_line.py
figular/models.py
figular/concept/__init__.py
figular/concept/circle.asy
figular/figular/__init__.py
figular/figular/cleanse.asy
figular/figular/date.asy
figular/figular/dom.asy
figular/figular/domtree.asy
figular/figular/element.asy
figular/figular/logger.asy
figular/figular/page.asy
figular/figular/paramsolver.asy
figular/figular/primitives.asy
figular/figular/selector.asy
figular/figular/style.asy
figular/figular/styledom.asy
figular/figular/stylereset.asy
figular/org/__init__.py
figular/org/orgchart.asy
figular/time/__init__.py
figular/time/timeline.asy
figular-0.0.17.dist-info/AGPL-3.0-or-later.txt
figular-0.0.17.dist-info/CC-BY-4.0.txt
figular-0.0.17.dist-info/CC-BY-SA-4.0.txt
figular-0.0.17.dist-info/METADATA
figular-0.0.17.dist-info/WHEEL
figular-0.0.17.dist-info/entry_points.txt
figular-0.0.17.dist-info/top_level.txt
figular-0.0.17.dist-info/RECORD
