Metadata-Version: 2.1
Name: figular
Version: 0.0.17
Summary: Figular generates visualisations from flexible, reusable parts
Home-page: https://figular.com/
Author: Galagic Limited
Author-email: info@figular.com
License: AGPL-3.0-or-later AND CC-BY-4.0 AND CC-BY-SA-4.0
Project-URL: Bug Tracker, https://gitlab.com/thegalagic/figular/-/issues
Project-URL: Changelog, https://gitlab.com/thegalagic/figular/-/releases
Project-URL: Source, https://gitlab.com/thegalagic/figular
Classifier: Development Status :: 4 - Beta
Classifier: Environment :: Console
Classifier: Environment :: Web Environment
Classifier: Intended Audience :: Developers
Classifier: Intended Audience :: End Users/Desktop
Classifier: License :: OSI Approved :: GNU Affero General Public License v3 or later (AGPLv3+)
Classifier: Operating System :: POSIX
Classifier: Programming Language :: Python :: 3
Classifier: Topic :: Multimedia :: Graphics
Classifier: Topic :: Utilities
License-File: LICENSES/AGPL-3.0-or-later.txt
License-File: LICENSES/CC-BY-4.0.txt
License-File: LICENSES/CC-BY-SA-4.0.txt
Requires-Dist: pydantic (!=1.7,!=1.7.1,!=1.7.2,!=1.7.3,!=1.8,!=1.8.1,<2.0.0,>=1.6.2)
